{
  "dependencies": [
    {
      "name": "@types/node",
      "version": "^14",
      "type": "build"
    },
    {
      "name": "npm-check-updates",
      "version": "^16",
      "type": "build"
    },
    {
      "name": "projen",
      "type": "build"
    },
    {
      "name": "ts-node",
      "type": "build"
    },
    {
      "name": "typescript",
      "type": "build"
    },
    {
      "name": "constructs",
      "version": "^10.1.241",
      "type": "runtime"
    },
    {
      "name": "projen",
      "type": "runtime"
    }
  ],
  "//": "~~ Generated by projen. To modify, edit .projenrc.js and run \"npx projen\"."
}
